embag-0.0.42.dist-info/top_level.txt
embag-0.0.42.dist-info/WHEEL
embag-0.0.42.dist-info/METADATA
embag-0.0.42.dist-info/RECORD
embag-0.0.42.dist-info/LICENSE
embag/libembag.so
embag/__init__.py
