Metadata-Version: 2.1
Name: embag
Version: 0.0.42
Summary: Fast ROS bag reader
Home-page: https://github.com/embarktrucks/embag
Author: Jason Snell
Author-email: jason@embarktrucks.com
License: MIT
Download-URL: https://pypi.org/project/embag/
Keywords: ROS,bag,reader
Platform: UNKNOWN
Classifier: Development Status :: 4 - Beta
Classifier: Intended Audience :: Developers
Classifier: Intended Audience :: Science/Research
Classifier: License :: OSI Approved :: MIT License
Classifier: Operating System :: POSIX
Classifier: Operating System :: MacOS
Classifier: Programming Language :: Python :: 2
Classifier: Programming Language :: Python :: 2.7
Classifier: Programming Language :: Python :: 3
Classifier: Programming Language :: Python :: 3.5
Classifier: Programming Language :: Python :: 3.6
Classifier: Programming Language :: Python :: 3.7
Classifier: Programming Language :: Python :: 3.8
Classifier: Programming Language :: Python :: 3.9
